Matrix/__init__.py
Matrix/matrix.py
Tree/Tree.py
Tree/__init__.py
Tree/read.py
Tree/supertree.py
api/__init__.py
api/api.py
pylogenetics/Matrix.py
pylogenetics/Tree.py
pylogenetics/__init__.py
pylogenetics/api.py
pylogenetics/matrix.py
pylogenetics/read.py
pylogenetics/stats.py
pylogenetics/supertree.py
pylogenetics-0.4.0.dist-info/METADATA
pylogenetics-0.4.0.dist-info/RECORD
pylogenetics-0.4.0.dist-info/WHEEL
pylogenetics-0.4.0.dist-info/pbr.json
pylogenetics-0.4.0.dist-info/top_level.txt
